osc_controller-0.3.0.dist-info/METADATA
osc_controller-0.3.0.dist-info/RECORD
osc_controller-0.3.0.dist-info/WHEEL
osc_controller-0.3.0.dist-info/top_level.txt
osccontroller/__init__.py
osccontroller/command_line_interface.py
osccontroller/graphical_inrerface.py
osccontroller/graphical_interface.py
osccontroller/helpers.py
osccontroller/option_containers.py
osccontroller/osc_client.py
osccontroller/simple_graphical_inrerface.py
