Metadata-Version: 2.1
Name: osc-controller
Version: 0.3.0
Summary: Simple library for creating osc software in python
Home-page: https://github.com/gogo2/osc-controller
Author: Bartosz Sobol
Author-email: bartoszmsobol@gmail.com
License: UNKNOWN
Platform: any
Classifier: Programming Language :: Python :: 3
Classifier: License :: OSI Approved :: MIT License
Classifier: Operating System :: OS Independent
